rapidtune/__init__.py
rapidtune-0.0.0.dist-info/METADATA
rapidtune-0.0.0.dist-info/WHEEL
rapidtune-0.0.0.dist-info/top_level.txt
rapidtune-0.0.0.dist-info/RECORD
