Metadata-Version: 2.4
Name: rapidtune
Version: 0.0.0
Summary: A one-line decorator to automatically speed up pytorch ops on GPU.
Author-email: Roland Tannous <rolandtannous@gravityq.ai>
